README.txt
setup.cfg
setup.py
Products/__init__.py
Products.FamFamFam.egg-info/PKG-INFO
Products.FamFamFam.egg-info/SOURCES.txt
Products.FamFamFam.egg-info/dependency_links.txt
Products.FamFamFam.egg-info/entry_points.txt
Products.FamFamFam.egg-info/namespace_packages.txt
Products.FamFamFam.egg-info/not-zip-safe
Products.FamFamFam.egg-info/requires.txt
Products.FamFamFam.egg-info/top_level.txt
Products/FamFamFam/__init__.py
Products/FamFamFam/config.py
Products/FamFamFam/configure.zcml
Products/FamFamFam/refresh.txt
Products/FamFamFam/version.txt
Products/FamFamFam/profiles/default/cssregistry.xml
Products/FamFamFam/profiles/default/metadata.xml
Products/FamFamFam/profiles/default/skins.xml
Products/FamFamFam/skins/famfamfam/add_alternative_icon.png
Products/FamFamFam/skins/famfamfam/add_icon.png
Products/FamFamFam/skins/famfamfam/application.png
Products/FamFamFam/skins/famfamfam/audio.png
Products/FamFamFam/skins/famfamfam/avi.png
Products/FamFamFam/skins/famfamfam/book_icon.png
Products/FamFamFam/skins/famfamfam/confirm_icon.png
Products/FamFamFam/skins/famfamfam/contentrules_icon.png
Products/FamFamFam/skins/famfamfam/contenttypes-sprite.png
Products/FamFamFam/skins/famfamfam/copy_icon.png
Products/FamFamFam/skins/famfamfam/cut_icon.png
Products/FamFamFam/skins/famfamfam/delete_icon.png
Products/FamFamFam/skins/famfamfam/discussionitem_icon.png
Products/FamFamFam/skins/famfamfam/discussionitemadd_icon.png
Products/FamFamFam/skins/famfamfam/discussionitemdelete_icon.png
Products/FamFamFam/skins/famfamfam/discussionitemreply_icon.png
Products/FamFamFam/skins/famfamfam/doc.png
Products/FamFamFam/skins/famfamfam/document_icon.png
Products/FamFamFam/skins/famfamfam/download_icon.png
Products/FamFamFam/skins/famfamfam/edit.png
Products/FamFamFam/skins/famfamfam/edit_inline.png
Products/FamFamFam/skins/famfamfam/error_icon.png
Products/FamFamFam/skins/famfamfam/error_log_icon.png
Products/FamFamFam/skins/famfamfam/event_icon.png
Products/FamFamFam/skins/famfamfam/exe.png
Products/FamFamFam/skins/famfamfam/extedit_icon.png
Products/FamFamFam/skins/famfamfam/famfamfam.css.dtml
Products/FamFamFam/skins/famfamfam/file_icon.png
Products/FamFamFam/skins/famfamfam/flag-plone.png
Products/FamFamFam/skins/famfamfam/folder.png
Products/FamFamFam/skins/famfamfam/folder_icon.png
