Metadata-Version: 1.0
Name: Products.FamFamFam
Version: 2.0
Summary: Collection of icons (FamFamFam) to replace the plone default ones
Home-page: http://plone.org/products/famfamfam
Author: Raptus AG
Author-email: dev@raptus.com
License: GPL
Keywords: Plone Icons FamFamFam
Platform: UNKNOWN
Classifier: Programming Language :: Python
Classifier: Topic :: Software Development :: Libraries :: Python Modules
